Jeb/__init__.py
Jeb/module.py
Jynweb-0.1.dist-info/LICENSE
Jynweb-0.1.dist-info/METADATA
Jynweb-0.1.dist-info/WHEEL
Jynweb-0.1.dist-info/top_level.txt
Jynweb-0.1.dist-info/RECORD
